LICENSE
MANIFEST.in
README.md
setup.py
wagtail_nhsuk_frontend.egg-info/PKG-INFO
wagtail_nhsuk_frontend.egg-info/SOURCES.txt
wagtail_nhsuk_frontend.egg-info/dependency_links.txt
wagtail_nhsuk_frontend.egg-info/requires.txt
wagtail_nhsuk_frontend.egg-info/top_level.txt
wagtailnhsukfrontend/__init__.py
wagtailnhsukfrontend/blocks.py
wagtailnhsukfrontend/mixins.py
wagtailnhsukfrontend/forms/__init__.py
wagtailnhsukfrontend/forms/apps.py
wagtailnhsukfrontend/forms/renderers.py
wagtailnhsukfrontend/forms/templates/django/forms/widgets/checkbox_select.html
wagtailnhsukfrontend/forms/templates/django/forms/widgets/input_option.html
wagtailnhsukfrontend/forms/templates/django/forms/widgets/multiple_input.html
wagtailnhsukfrontend/forms/templates/django/forms/widgets/radio.html
wagtailnhsukfrontend/forms/templates/forms/form_as_div.html
wagtailnhsukfrontend/forms/templatetags/__init__.py
wagtailnhsukfrontend/forms/templatetags/nhsukfrontendforms_tags.py
wagtailnhsukfrontend/migrations/__init__.py
wagtailnhsukfrontend/settings/__init__.py
wagtailnhsukfrontend/settings/apps.py
wagtailnhsukfrontend/settings/models.py
wagtailnhsukfrontend/settings/migrations/0001_initial.py
wagtailnhsukfrontend/settings/migrations/0002_emergencyalert.py
wagtailnhsukfrontend/settings/migrations/0003_footersettings.py
wagtailnhsukfrontend/settings/migrations/0004_footersettings_fixed_coloumn_footer.py
wagtailnhsukfrontend/settings/migrations/0005_remove_emergency_alert.py
wagtailnhsukfrontend/settings/migrations/0006_remove_footersettings_fixed_coloumn_footer.py
wagtailnhsukfrontend/settings/migrations/0007_organisational_header.py
wagtailnhsukfrontend/settings/migrations/__init__.py
wagtailnhsukfrontend/settings/templatetags/__init__.py
wagtailnhsukfrontend/settings/templatetags/nhsukfrontendsettings_tags.py
wagtailnhsukfrontend/static/wagtailnhsukfrontend/css/nhsuk.min.css
wagtailnhsukfrontend/static/wagtailnhsukfrontend/favicons/apple-touch-icon-180x180.png
wagtailnhsukfrontend/static/wagtailnhsukfrontend/favicons/apple-touch-icon.png
wagtailnhsukfrontend/static/wagtailnhsukfrontend/favicons/favicon-192x192.png
wagtailnhsukfrontend/static/wagtailnhsukfrontend/favicons/favicon.ico
