Metadata-Version: 2.1
Name: wagtail-nhsuk-frontend
Version: 1.5.1
Summary: NHSUK Frontend Styles for Wagtail
Home-page: https://github.com/nhsuk/wagtail-nhsuk-frontend
Author: Dominic Baker
Author-email: <dominic.baker1@nhs.net>
Provides-Extra: testing
Provides-Extra: linting
License-File: LICENSE
